{
    "type": "FeatureCollection",
    "name": "geobase_mtl",
    "features": [
        {
            "type": "Feature",
            "geometry": {
                "type": "LineString",
                "coordinates": [
                    [
                        -73.74080484082164,
                        45.518959558860786
                    ],
                    [
                        -73.74087499736882,
                        45.51898934909444
                    ],
                    [
                        -73.74092676228376,
                        45.51902127717946
                    ],
                    [
                        -73.74188670722779,
                        45.519640108602225
                    ],
                    [
                        -73.74196852084071,
                        45.519695221084056
                    ]
                ]
            },
            "properties": {
                "ID_TRC": 1010001,
                "DEB_GCH": 12320,
                "FIN_GCH": 12340,
                "ARR_GCH": "Ahuntsic-Cartierville",
                "SENS_CIR": 0,
                "CLASSE": 0,
                "LIE_VOIE": null,
                "TYP_VOIE": "avenue",
                "DIR_VOIE": null,
                "NOM_VOIE": "Adhémar-Mailhiot",
                "DEB_DRT": 12323,
                "FIN_DRT": 12335,
                "ARR_DRT": "Ahuntsic-Cartierville",
                "LIM_GCH": "Montréal",
                "LIM_DRT": "Montréal",
                "POSITION": 5,
                "ODONYME": "Avenue Adhémar-Mailhiot "
            },
            "capacity": 3
        },
        {
            "type": "Feature",
            "geometry": {
                "type": "LineString",
                "coordinates": [
                    [
                        -73.70623530423325,
                        45.527646493721306
                    ],
                    [
                        -73.70629430924254,
                        45.52759778866121
                    ],
                    [
                        -73.7066906006261,
                        45.52727777851528
                    ],
                    [
                        -73.70671238591936,
                        45.52725785084725
                    ],
                    [
                        -73.7067274208916,
                        45.527240095005574
                    ],
                    [
                        -73.70673392212828,
                        45.52722766433297
                    ],
                    [
                        -73.70674081687976,
                        45.5272073134621
                    ],
                    [
                        -73.70674125317629,
                        45.52718220468139
                    ],
                    [
                        -73.70673739506634,
                        45.52716673285305
                    ],
                    [
                        -73.70673249273064,
                        45.52715450278576
                    ],
                    [
                        -73.70671879388978,
                        45.52713346931191
                    ],
                    [
                        -73.7067027913941,
                        45.527117659522766
                    ],
                    [
                        -73.70598918338321,
                        45.52665575670475
                    ],
                    [
                        -73.70594008055075,
                        45.526626507550006
                    ],
                    [
                        -73.70592368938513,
                        45.52661987761266
                    ],
                    [
                        -73.70588955127046,
                        45.52661129978933
                    ],
                    [
                        -73.70586238092204,
                        45.52660895270981
                    ],
                    [
                        -73.70582259798886,
                        45.526609440797735
                    ],
                    [
                        -73.7058045516517,
                        45.52661226303902
                    ],
                    [
                        -73.7057696380703,
                        45.526622764971755
                    ],
                    [
                        -73.70575540622154,
                        45.526629180141576
                    ],
                    [
                        -73.7057274845586,
                        45.52664578905009
                    ],
                    [
                        -73.70527461392626,
                        45.52694249950405
                    ],
                    [
                        -73.70521700121,
                        45.52699117432167
                    ]
                ]
            },
            "properties": {
                "ID_TRC": 1010004,
                "DEB_GCH": 5530,
                "FIN_GCH": 5570,
                "ARR_GCH": "Ahuntsic-Cartierville",
                "SENS_CIR": 0,
                "CLASSE": 0,
                "LIE_VOIE": null,
                "TYP_VOIE": "place",
                "DIR_VOIE": null,
                "NOM_VOIE": "D'Aiguillon",
                "DEB_DRT": 5475,
                "FIN_DRT": 5625,
                "ARR_DRT": "Ahuntsic-Cartierville",
                "LIM_GCH": "Montréal",
                "LIM_DRT": "Montréal",
                "POSITION": 5,
                "ODONYME": "Place D'Aiguillon "
            },
            "capacity": 3
        },
        {
            "type": "Feature",
            "geometry": {
                "type": "LineString",
                "coordinates": [
                    [
                        -73.73715005426241,
                        45.52446169319431
                    ],
                    [
                        -73.73721324929674,
                        45.524410073150115
                    ],
                    [
                        -73.73880840048504,
                        45.523137942696124
                    ],
                    [
                        -73.7388752626822,
                        45.523085116816716
                    ]
                ]
            },
            "properties": {
                "ID_TRC": 1010005,
                "DEB_GCH": 7750,
                "FIN_GCH": 7830,
                "ARR_GCH": "Ahuntsic-Cartierville",
                "SENS_CIR": 0,
                "CLASSE": 0,
                "LIE_VOIE": null,
                "TYP_VOIE": "avenue",
                "DIR_VOIE": null,
                "NOM_VOIE": "Albert-LeSage",
                "DEB_DRT": 7745,
                "FIN_DRT": 7805,
                "ARR_DRT": "Ahuntsic-Cartierville",
                "LIM_GCH": "Montréal",
                "LIM_DRT": "Montréal",
                "POSITION": 5,
                "ODONYME": "Avenue Albert-LeSage "
            },
            "capacity": 3
        },
        {
            "type": "Feature",
            "geometry": {
                "type": "LineString",
                "coordinates": [
                    [
                        -73.6515978833292,
                        45.58573015879556
                    ],
                    [
                        -73.6516882177041,
                        45.585740325739664
                    ],
                    [
                        -73.65202155877037,
                        45.585777842413336
                    ],
                    [
                        -73.65207643383332,
                        45.58578554458162
                    ],
                    [
                        -73.65211612460487,
                        45.585794249332885
                    ],
                    [
                        -73.65276562173818,
                        45.58593806089942
                    ],
                    [
                        -73.652786462828,
                        45.58594045424515
                    ],
                    [
                        -73.65280854332809,
                        45.58594007310316
                    ],
                    [
                        -73.6528460478978,
                        45.58593000984676
                    ]
                ]
            },
            "properties": {
                "ID_TRC": 1610155,
                "DEB_GCH": 11134,
                "FIN_GCH": 11174,
                "ARR_GCH": "Montréal-Nord",
                "SENS_CIR": 1,
                "CLASSE": 0,
                "LIE_VOIE": null,
                "TYP_VOIE": "avenue",
                "DIR_VOIE": null,
                "NOM_VOIE": "Cadieux",
                "DEB_DRT": 11145,
                "FIN_DRT": 11219,
                "ARR_DRT": "Montréal-Nord",
                "LIM_GCH": "Montréal",
                "LIM_DRT": "Montréal",
                "POSITION": 5,
                "ODONYME": "Avenue Cadieux "
            },
            "capacity": 3
        },
        {
            "type": "Feature",
            "geometry": {
                "type": "LineString",
                "coordinates": [
                    [
                        -73.81997012115698,
                        45.482770122178714
                    ],
                    [
                        -73.82002528958759,
                        45.48282876494676
                    ],
                    [
                        -73.82056043888237,
                        45.48340385177692
                    ],
                    [
                        -73.82057856716573,
                        45.483418919670214
                    ],
                    [
                        -73.82061766237827,
                        45.48344724801279
                    ],
                    [
                        -73.82066022427313,
                        45.483472956605965
                    ],
                    [
                        -73.82070593567784,
                        45.48349577660746
                    ],
                    [
                        -73.82075479562957,
                        45.48351561780664
                    ],
                    [
                        -73.82078143677698,
                        45.483524722327175
                    ],
                    [
                        -73.82117557257253,
                        45.48362503739432
                    ],
                    [
                        -73.82128344814839,
                        45.48365255952722
                    ]
                ]
            },
            "properties": {
                "ID_TRC": 1621266,
                "DEB_GCH": 1154,
                "FIN_GCH": 1160,
                "ARR_GCH": "N/A",
                "SENS_CIR": 0,
                "CLASSE": 5,
                "LIE_VOIE": null,
                "TYP_VOIE": "rue",
                "DIR_VOIE": null,
                "NOM_VOIE": "Tecumseh",
                "DEB_DRT": 1151,
                "FIN_DRT": 1159,
                "ARR_DRT": "N/A",
                "LIM_GCH": "Dollard-des-Ormeaux",
                "LIM_DRT": "Dollard-des-Ormeaux",
                "POSITION": 5,
                "ODONYME": "Rue Tecumseh "
            },
            "capacity": 3
        },
        {
            "type": "Feature",
            "geometry": {
                "type": "LineString",
                "coordinates": [
                    [
                        -73.81852061179298,
                        45.48263247805027
                    ],
                    [
                        -73.81847287265339,
                        45.48258283232703
                    ],
                    [
                        -73.81816815601422,
                        45.482264475110014
                    ],
                    [
                        -73.81815489601838,
                        45.48225182308248
                    ],
                    [
                        -73.81814334915146,
                        45.482243575755
                    ],
                    [
                        -73.81813118499015,
                        45.482238210104356
                    ],
                    [
                        -73.81812008620622,
                        45.482234641178444
                    ],
                    [
                        -73.8181050864535,
                        45.48223162324791
                    ],
                    [
                        -73.81809241920612,
                        45.48223057848244
                    ],
                    [
                        -73.81807954716648,
                        45.48223061432661
                    ],
                    [
                        -73.81806815869761,
                        45.48223181606381
                    ],
                    [
                        -73.818053300558,
                        45.48223518709242
                    ],
                    [
                        -73.81804303166788,
                        45.48223835074965
                    ],
                    [
                        -73.81802698113901,
                        45.482245519747565
                    ],
                    [
                        -73.81795911058315,
                        45.482278286282046
                    ],
                    [
                        -73.81794554739541,
                        45.48228678326714
                    ],
                    [
                        -73.81793348144119,
                        45.48229887614433
                    ],
                    [
                        -73.81792867181507,
                        45.48230662888589
                    ],
                    [
                        -73.81792534277822,
                        45.482315097383605
                    ],
                    [
                        -73.81792395487253,
                        45.48233094011987
                    ],
                    [
                        -73.8179256907601,
                        45.48233939474555
                    ],
                    [
                        -73.81792932740437,
                        45.48234820401945
                    ],
                    [
                        -73.81793814982102,
                        45.482359698623966
                    ],
                    [
                        -73.81824881567505,
                        45.482685419290206
                    ],
                    [
                        -73.81829661510042,
                        45.482736805916105
                    ]
                ]
            },
            "properties": {
                "ID_TRC": 1621267,
                "DEB_GCH": 0,
                "FIN_GCH": 0,
                "ARR_GCH": "N/A",
                "SENS_CIR": 1,
                "CLASSE": 0,
                "LIE_VOIE": null,
                "TYP_VOIE": "rue",
                "DIR_VOIE": null,
                "NOM_VOIE": "Montevista",
                "DEB_DRT": 102,
                "FIN_DRT": 116,
                "ARR_DRT": "N/A",
                "LIM_GCH": "Dollard-des-Ormeaux",
                "LIM_DRT": "Dollard-des-Ormeaux",
                "POSITION": 5,
                "ODONYME": "Rue Montevista "
            },
            "capacity": 3
        },
        {
            "type": "Feature",
            "geometry": {
                "type": "LineString",
                "coordinates": [
                    [
                        -73.85164011415523,
                        45.48151514719277
                    ],
                    [
                        -73.8516517561285,
                        45.48150395212966
                    ],
                    [
                        -73.85165929840079,
                        45.48149519949769
                    ],
                    [
                        -73.85166627532256,
                        45.48148041918292
                    ],
                    [
                        -73.85166946223937,
                        45.481466910321316
                    ],
                    [
                        -73.85167025128672,
                        45.481458088494605
                    ],
                    [
                        -73.85166763791717,
                        45.48144504763834
                    ],
                    [
                        -73.85166059825413,
                        45.48143283004589
                    ],
                    [
                        -73.85165358882665,
                        45.481425472206965
                    ],
                    [
                        -73.85163282560956,
                        45.48141203707488
                    ],
                    [
                        -73.8514392619075,
                        45.481348124780936
                    ],
                    [
                        -73.85140951437823,
                        45.48133695471819
                    ],
                    [
                        -73.85137817528826,
                        45.48132045930147
                    ]
                ]
            },
            "properties": {
                "ID_TRC": 4005503,
                "DEB_GCH": 0,
                "FIN_GCH": 0,
                "ARR_GCH": "Pierrefonds-Roxboro",
                "SENS_CIR": 0,
                "CLASSE": 0,
                "LIE_VOIE": null,
                "TYP_VOIE": "rue",
                "DIR_VOIE": null,
                "NOM_VOIE": "Juneau",
                "DEB_DRT": 4269,
                "FIN_DRT": 4275,
                "ARR_DRT": "Pierrefonds-Roxboro",
                "LIM_GCH": "Montréal",
                "LIM_DRT": "Montréal",
                "POSITION": 5,
                "ODONYME": "Rue Juneau "
            },
            "capacity": 3
        },
        {
            "type": "Feature",
            "geometry": {
                "type": "LineString",
                "coordinates": [
                    [
                        -73.64903987591468,
                        45.50689121745027
                    ],
                    [
                        -73.64904808919913,
                        45.50684351058382
                    ],
                    [
                        -73.64904922357688,
                        45.506833429968125
                    ],
                    [
                        -73.64905098892054,
                        45.50682244846168
                    ],
                    [
                        -73.64905411905278,
                        45.50680858545346
                    ],
                    [
                        -73.6490585146788,
                        45.50679427087257
                    ],
                    [
                        -73.64906312670242,
                        45.5067818456783
                    ],
                    [
                        -73.64906910828996,
                        45.50676851907904
                    ],
                    [
                        -73.64907562012162,
                        45.506756181389235
                    ],
                    [
                        -73.64908255599025,
                        45.50674447326032
                    ],
                    [
                        -73.64909107306983,
                        45.506731953208984
                    ],
                    [
                        -73.64909906705252,
                        45.50672132373395
                    ],
                    [
                        -73.64912503136654,
                        45.50668025297421
                    ]
                ]
            },
            "properties": {
                "ID_TRC": 4011472,
                "DEB_GCH": 0,
                "FIN_GCH": 0,
                "ARR_GCH": "N/A",
                "SENS_CIR": -1,
                "CLASSE": 0,
                "LIE_VOIE": null,
                "TYP_VOIE": "chemin",
                "DIR_VOIE": null,
                "NOM_VOIE": "Saint-Clare",
                "DEB_DRT": 0,
                "FIN_DRT": 0,
                "ARR_DRT": "N/A",
                "LIM_GCH": "Mont-Royal",
                "LIM_DRT": "Mont-Royal",
                "POSITION": 5,
                "ODONYME": "Chemin Saint-Clare "
            },
            "capacity": 3
        },
        {
            "type": "Feature",
            "geometry": {
                "type": "LineString",
                "coordinates": [
                    [
                        -73.55620574801648,
                        45.593293505227166
                    ],
                    [
                        -73.55617047018424,
                        45.593294217696155
                    ],
                    [
                        -73.55614974816802,
                        45.59329737885847
                    ],
                    [
                        -73.55612592761474,
                        45.59330406324417
                    ],
                    [
                        -73.5560990105503,
                        45.59331630986226
                    ],
                    [
                        -73.556078300244,
                        45.5933312407659
                    ],
                    [
                        -73.55606076537966,
                        45.59335321374196
                    ],
                    [
                        -73.5560506914734,
                        45.59337824112281
                    ],
                    [
                        -73.55605117677703,
                        45.59340159526475
                    ],
                    [
                        -73.55606096988537,
                        45.59342614971003
                    ],
                    [
                        -73.55607775434842,
                        45.593445696100176
                    ],
                    [
                        -73.5561085326884,
                        45.593466440486246
                    ],
                    [
                        -73.55613996909061,
                        45.5934853308934
                    ],
                    [
                        -73.5561624347956,
                        45.59350997155866
                    ],
                    [
                        -73.55617539366189,
                        45.593532207603246
                    ],
                    [
                        -73.55618331047629,
                        45.593557458302726
                    ]
                ]
            },
            "properties": {
                "ID_TRC": 4018264,
                "DEB_GCH": 0,
                "FIN_GCH": 0,
                "ARR_GCH": "Anjou",
                "SENS_CIR": 1,
                "CLASSE": 0,
                "LIE_VOIE": "de la",
                "TYP_VOIE": "avenue",
                "DIR_VOIE": null,
                "NOM_VOIE": "Nantaise",
                "DEB_DRT": 0,
                "FIN_DRT": 0,
                "ARR_DRT": "Anjou",
                "LIM_GCH": "Montréal",
                "LIM_DRT": "Montréal",
                "POSITION": 5,
                "ODONYME": "Avenue de la Nantaise "
            },
            "capacity": 3
        },
        {
            "type": "Feature",
            "geometry": {
                "type": "LineString",
                "coordinates": [
                    [
                        -73.64701850208269,
                        45.47934257293711
                    ],
                    [
                        -73.6470949040875,
                        45.47937572256836
                    ],
                    [
                        -73.64793149997743,
                        45.4797537843224
                    ],
                    [
                        -73.64795379261922,
                        45.47976563455222
                    ],
                    [
                        -73.64797481822688,
                        45.47977694628603
                    ],
                    [
                        -73.64800860770666,
                        45.47978743184114
                    ],
                    [
                        -73.64802665638082,
                        45.479790108218914
                    ],
                    [
                        -73.64804353992169,
                        45.47979098641038
                    ],
                    [
                        -73.64806379482965,
                        45.479790240055344
                    ],
                    [
                        -73.64808182959902,
                        45.47978760689667
                    ],
                    [
                        -73.64809943815966,
                        45.479783264353934
                    ],
                    [
                        -73.64811514361742,
                        45.47977757450604
                    ],
                    [
                        -73.64812884238978,
                        45.4797709871865
                    ],
                    [
                        -73.64814274612672,
                        45.47976214975763
                    ],
                    [
                        -73.6481547472307,
                        45.479752144994016
                    ],
                    [
                        -73.64816484683264,
                        45.47974106265448
                    ],
                    [
                        -73.64818208554136,
                        45.47971638224224
                    ],
                    [
                        -73.64818869799754,
                        45.4797032345516
                    ],
                    [
                        -73.64819488544559,
                        45.479689007595816
                    ],
                    [
                        -73.64820665416714,
                        45.479670633653306
                    ],
                    [
                        -73.64928250545894,
                        45.47847304086219
                    ],
                    [
                        -73.64933455124036,
                        45.4784156609051
                    ]
                ]
            },
            "properties": {
                "ID_TRC": 4006594,
                "DEB_GCH": 70,
                "FIN_GCH": 88,
                "ARR_GCH": "N/A",
                "SENS_CIR": 0,
                "CLASSE": 0,
                "LIE_VOIE": null,
                "TYP_VOIE": "rue",
                "DIR_VOIE": null,
                "NOM_VOIE": "Downshire",
                "DEB_DRT": 63,
                "FIN_DRT": 89,
                "ARR_DRT": "N/A",
                "LIM_GCH": "Hampstead",
                "LIM_DRT": "Hampstead",
                "POSITION": 5,
                "ODONYME": "Rue Downshire "
            },
            "capacity": 3
        },
        {
            "type": "Feature",
            "geometry": {
                "type": "LineString",
                "coordinates": [
                    [
                        -73.93130202214127,
                        45.40617709009385
                    ],
                    [
                        -73.93130120973458,
                        45.40623648968265
                    ],
                    [
                        -73.93128624835002,
                        45.40636127850844
                    ],
                    [
                        -73.93125468498496,
                        45.406579428704305
                    ],
                    [
                        -73.93111641772767,
                        45.40743123484014
                    ],
                    [
                        -73.93104025584242,
                        45.40797445928792
                    ],
                    [
                        -73.93097561817748,
                        45.408412076647735
                    ],
                    [
                        -73.93084346304924,
                        45.40921379618173
                    ],
                    [
                        -73.93072496258185,
                        45.409982436244064
                    ],
                    [
                        -73.93071688253698,
                        45.41002805802234
                    ]
                ]
            },
            "properties": {
                "ID_TRC": 1618983,
                "DEB_GCH": 40,
                "FIN_GCH": 82,
                "ARR_GCH": "N/A",
                "SENS_CIR": 0,
                "CLASSE": 0,
                "LIE_VOIE": null,
                "TYP_VOIE": "rue",
                "DIR_VOIE": null,
                "NOM_VOIE": "Saint-Andrew's",
                "DEB_DRT": 35,
                "FIN_DRT": 65,
                "ARR_DRT": "N/A",
                "LIM_GCH": "Baie-d'Urfé",
                "LIM_DRT": "Baie-d'Urfé",
                "POSITION": 5,
                "ODONYME": "Rue Saint-Andrew's "
            },
            "capacity": 3
        }
    ]
}